pn532pi/__init__.py
pn532pi/interfaces/__init__.py
pn532pi/interfaces/pn532Interface.py
pn532pi/interfaces/pn532hsu.py
pn532pi/interfaces/pn532i2c.py
pn532pi/interfaces/pn532spi.py
pn532pi/nfc/__init__.py
pn532pi/nfc/emulatetag.py
pn532pi/nfc/llcp.py
pn532pi/nfc/macLink.py
pn532pi/nfc/pn532.py
pn532pi/nfc/pn532_log.py
pn532pi/nfc/snep.py
quick2wire/__init__.py
quick2wire/asm_generic_ioctl.py
quick2wire/board_revision.py
quick2wire/eventfd.py
quick2wire/gpio.py
quick2wire/i2c.py
quick2wire/i2c_ctypes.py
quick2wire/selector.py
quick2wire/spi.py
quick2wire/spi_ctypes.py
quick2wire/syscall.py
quick2wire/test_eventfd.py
quick2wire/test_gpio.py
quick2wire/test_gpio_loopback.py
quick2wire/test_selector.py
quick2wire/test_spi_loopback.py
quick2wire/test_timerfd.py
quick2wire/timerfd.py
quick2wire/helpers/__init__.py
quick2wire/helpers/display.py
quick2wire/parts/__init__.py
quick2wire/parts/mcp23017.py
quick2wire/parts/mcp23x17.py
quick2wire/parts/pcf8591.py
quick2wire/parts/test_mcp23017_interrupts_loopback.py
quick2wire/parts/test_mcp23017_loopback.py
quick2wire/parts/test_mcp23x17.py
quick2wire/parts/test_pcf8591.py
quick2wire/parts/test_pcf8591_loopback.py
pn532pi-1.7.dist-info/METADATA
pn532pi-1.7.dist-info/WHEEL
pn532pi-1.7.dist-info/top_level.txt
pn532pi-1.7.dist-info/RECORD
