Metadata-Version: 2.1
Name: pn532pi
Version: 1.7
Summary: PN532 library for Raspberry Pi
Home-page: https://github.com/gassajor000/pn532pi
Author: gassajor000
Author-email: 43421414+gassajor000@users.noreply.github.com
Classifier: Programming Language :: Python :: 3
Classifier: License :: OSI Approved :: BSD License 
Classifier: Operating System :: POSIX :: Linux
Requires-Python: >=3.4
Requires-Dist: pyserial
Requires-Dist: spidev
Requires-Dist: typing
